vibe_math_mcp/__init__.py
vibe_math_mcp/core/__init__.py
vibe_math_mcp/core/batch_executor.py
vibe_math_mcp/core/batch_models.py
vibe_math_mcp/core/converters.py
vibe_math_mcp/core/formatters.py
vibe_math_mcp/core/result_resolver.py
vibe_math_mcp/core/validators.py
vibe_math_mcp/http_server.py
vibe_math_mcp/py.typed
vibe_math_mcp/server.py
vibe_math_mcp/tools/__init__.py
vibe_math_mcp/tools/array.py
vibe_math_mcp/tools/basic.py
vibe_math_mcp/tools/batch.py
vibe_math_mcp/tools/calculus.py
vibe_math_mcp/tools/financial.py
vibe_math_mcp/tools/linalg.py
vibe_math_mcp/tools/statistics.py
vibe_math_mcp-2.0.3.dist-info/WHEEL
vibe_math_mcp-2.0.3.dist-info/entry_points.txt
vibe_math_mcp-2.0.3.dist-info/METADATA
vibe_math_mcp-2.0.3.dist-info/RECORD
