Metadata-Version: 2.4
Name: vibe-math-mcp
Version: 2.0.3
Summary: High-performance MCP server for mathematical operations using Polars and scientific Python
Keywords: mcp,math,mathematics,statistics,calculus,linear-algebra,finance,polars,numpy,scipy
Author: Akshay Petta
Author-email: Akshay Petta <33671231+apetta@users.noreply.github.com>
License-Expression: MIT
Classifier: Development Status :: 5 - Production/Stable
Classifier: Intended Audience :: Developers
Classifier: License :: OSI Approved :: MIT License
Classifier: Programming Language :: Python :: 3
Classifier: Programming Language :: Python :: 3.11
Classifier: Programming Language :: Python :: 3.12
Classifier: Programming Language :: Python :: 3.13
Classifier: Topic :: Scientific/Engineering :: Mathematics
Classifier: Topic :: Software Development :: Libraries :: Python Modules
Requires-Dist: fastmcp~=2.13.0
Requires-Dist: polars~=1.34.0
Requires-Dist: pandas~=2.3.3
Requires-Dist: numpy~=2.3.4
Requires-Dist: numpy-financial~=1.0.0
Requires-Dist: scipy~=1.16.2
Requires-Dist: sympy~=1.14.0
Requires-Dist: pydantic~=2.12.3
Requires-Dist: pyarrow~=22.0.0
Requires-Dist: uvicorn~=0.34.0
Requires-Dist: starlette~=0.41.0
Requires-Dist: pytest>=8.0.0 ; extra == 'dev'
Requires-Dist: pytest-asyncio>=0.23.0 ; extra == 'dev'
Requires-Dist: pytest-cov>=4.1.0 ; extra == 'dev'
Requires-Dist: ruff>=0.3.0 ; extra == 'dev'
Requires-Python: >=3.11
Provides-Extra: dev
